{"id": 1163897368040939520, "username": "amymcgrathky", "created_at": "2019-08-21 01:05:31 IST", "tweet": "Glad to meet LTC Jack Morrison, US Army Chaplain Corps (Ret.) in Elizabethtown today. Great T-shirt, sir!  https://t.co/BRZrOjBmVM", "replies_count": 24, "retweets_count": 211, "likes_count": 1323, "Follower_count": 579381, "id_str": "1163897368040939520"}
{"id": 1164191713889587200, "username": "peterlbrandt", "created_at": "2019-08-21 20:35:08 IST", "tweet": "It is not all peachy keen in Cryptoville. But hey, they are just lines and all critics of TA know that lines mean nothing. $BCH $XRP $LTC  https://t.co/GJq5L9jO9h", "replies_count": 124, "retweets_count": 156, "likes_count": 640, "Follower_count": 515797, "id_str": "1164191713889587200"}
{"id": 1164234248297046016, "username": "coindesk", "created_at": "2019-08-21 23:24:09 IST", "tweet": "BREAKING: @USTreasury's OFAC has put bitcoin and litecoin addresses of three Chinese nationals on its sanctions list, the second time the agency has blacklisted crypto wallets.    https://t.co/FRuuhFst5t  Report by @nikhileshde", "replies_count": 26, "retweets_count": 117, "likes_count": 213, "Follower_count": 1597769, "id_str": "1164234248297046016"}
{"id": 1163979675351310336, "username": "coindesk", "created_at": "2019-08-21 06:32:34 IST", "tweet": "Founded in 1881, the Austrian A1 mobile network is looking to add $DASH, $ETH, $LTC, $XLR, and $ as payment options.  https://t.co/k0hkGyZjfG via @wsfoxley", "replies_count": 14, "retweets_count": 65, "likes_count": 145, "Follower_count": 1597768, "id_str": "1163979675351310336"}
{"id": 1164103133448089605, "username": "woonomic", "created_at": "2019-08-21 14:43:09 IST", "tweet": "I'm building a chart that includes every coin, for its entire trading history. This is the earliest snapshot from Coinmarketcap; on Apr 2013, 7 coins listed.   Anyone have earlier market data specifically for TRC and DVC? #DataArchaeology  (I already have BTC LTC NVC NMC PPC)  https://t.co/Ncjn99iiZA", "replies_count": 19, "retweets_count": 33, "likes_count": 208, "Follower_count": 514936, "id_str": "1164103133448089605"}
{"id": 1164200415220654085, "username": "cryptokaleo", "created_at": "2019-08-21 21:09:43 IST", "tweet": "$LTC / $BTC  The line drawn is at .0068.  Litecoin has spent 1,681 days above the line (83% of its life) and 353 days below it (17%).  Every time it has hit or dipped below the line, it has recovered with at least a 200% gain.  It's probably not a bad time to start scaling in.  https://t.co/MC9NdVwISi", "replies_count": 6, "retweets_count": 20, "likes_count": 90, "Follower_count": 308338, "id_str": "1164200415220654085"}
{"id": 1163886442290061313, "username": "jonnylitecoin", "created_at": "2019-08-21 00:22:06 IST", "tweet": "Stopped in for a follow up visit at Full Auto Air Soft in Emerson, NJ!! Talking with the owner about a possible e-commerce site and he surprised me with the #Litecoin QR code as the new wallpaper for his iPad!! I will continue to spread #PayWithLitecoin all over the NJ area!!  https://t.co/nSITZnK4fc", "replies_count": 6, "retweets_count": 32, "likes_count": 152, "Follower_count": 14444, "id_str": "1163886442290061313"}
{"id": 1163883001153015808, "username": "cryptorecruitr", "created_at": "2019-08-21 00:08:26 IST", "tweet": "Litecoin charts looking like we\u2019ll be testing mid $80\u2019s soon  I will be very surprised if we make new lower lows before that", "replies_count": 19, "retweets_count": 11, "likes_count": 144, "Follower_count": 101450, "id_str": "1163883001153015808"}
{"id": 1163985711219073026, "username": "the_blocknet", "created_at": "2019-08-21 06:56:34 IST", "tweet": "With over 34,000 LTC atomic swaps completed on our @BlockDXExchange, we are anticipating the 0.18.1 Core update as Litecoin is a long time favorite of ours, our community, and Block DX traders given its size, speed, adoption, and solid foundational value! @SatoshiLite @litecoin", "replies_count": 0, "retweets_count": 22, "likes_count": 62, "Follower_count": 22731, "id_str": "1163985711219073026"}
{"id": 1164147212378615808, "username": "_theeagleflies_", "created_at": "2019-08-21 17:38:18 IST", "tweet": "New listing!  @H_O_L_O_ token (HOT) will be listed on @OceanexOfficial very soon!   #cryptocurrency #blockchain $hot  #eth #bitcoin #holochain #Holo #xrp\u00a0 #xrpcommmunity\u00a0 #eos\u00a0 #trx #dash #xmr #btt #bch\u00a0 #ltc #listing #exchange #elrond  https://t.co/7LziphO0iA", "replies_count": 1, "retweets_count": 24, "likes_count": 80, "Follower_count": 4452, "id_str": "1164147212378615808"}
{"id": 1164127452676775936, "username": "ninesnons02", "created_at": "2019-08-21 16:19:47 IST", "tweet": "My small contribution to the world of #crypto by sharing the different uses of #MCOVisaCard ! Today I can pay my train fare with #bitcoin #ltc and get 3% cashback as reward for it. This is awesome :-D #USA #Singapore get yours today with 50 usd free (Code : wea9dhngzt) #GOTMCO  https://t.co/KqN7Eo5TW8", "replies_count": 10, "retweets_count": 13, "likes_count": 108, "Follower_count": 361, "id_str": "1164127452676775936"}
{"id": 1164131349760040960, "username": "daddycool1991", "created_at": "2019-08-21 16:35:16 IST", "tweet": "The @LTCFoundation is: * only 2 years old  * promoting awareness &amp; adoption of LTC globally  * funded mostly by donations &amp; merch sales  * recognized &amp; reported as a leader in the #Crypto space  * doing all this on a shoestring budget  * supported by &gt;100 volunteers  * NOT an ICO  https://t.co/mpWZIFXfBu", "replies_count": 4, "retweets_count": 11, "likes_count": 80, "Follower_count": 10999, "id_str": "1164131349760040960"}
{"id": 1164111800784343041, "username": "val5linx", "created_at": "2019-08-21 15:17:36 IST", "tweet": "Adoption Folks! (in my best DAI voice)  The telecommunications giant will accept Dash, Ether (ETH), Litecoin (LTC), Stellar (XLM), and XRP, according to Austrian news outlet\u00a0Futurezone.\u00a0   https://t.co/9fuHiXvKmk", "replies_count": 2, "retweets_count": 19, "likes_count": 54, "Follower_count": 10899, "id_str": "1164111800784343041"}
{"id": 1164000001778999296, "username": "chainzillaio", "created_at": "2019-08-21 07:53:21 IST", "tweet": "Switching gears with #chameleonpay's payment options. Our team is now testing pre-paid giftcard purchases and mobile top-ups. @KomodoPlatform @ElectricCoinCo @litecoin @StablyCoin  https://t.co/BPiZa16Kep", "replies_count": 0, "retweets_count": 24, "likes_count": 44, "Follower_count": 5657, "id_str": "1164000001778999296"}
