{"id": 1029798399137202176, "username": "openlawofficial", "created_at": "2018-08-16 00:04:05 IST", "tweet": "The response to our partnership with @chainlink has been strong. Read more here about how we're working together to denominate smart contracts in $USD  https://t.co/vebJeA35kw", "replies_count": 4, "retweets_count": 25, "likes_count": 88, "Follower_count": 10423, "id_str": "1029798399137202176"}
{"id": 1030158860437401601, "username": "oly245", "created_at": "2018-08-16 23:56:26 IST", "tweet": "If you follow some of these influencers that shill complete shit coins, ask them why. I see so many coins shilled by people but no reasoning behind it. eg - $LINK I'm seeing a lot of. Whenever I tweet about a crypto I try to say why I think its a good buy.. these guys don't. \ud83e\uddd0\ud83d\ude44", "replies_count": 15, "retweets_count": 1, "likes_count": 23, "Follower_count": 47548, "id_str": "1030158860437401601"}
{"id": 1029967290232500230, "username": "le_lannister", "created_at": "2018-08-16 11:15:12 IST", "tweet": "Picked a fat moon bag of $LINK.", "replies_count": 5, "retweets_count": 2, "likes_count": 35, "Follower_count": 15578, "id_str": "1029967290232500230"}
{"id": 1030096642429480960, "username": "cryptofelixleon", "created_at": "2018-08-16 19:49:12 IST", "tweet": "Smart contracts interacting with the real world need to do so with end to end security, w/ trust. There is no point of having a tamper proof execution if the data coming in is not trusted. #Chainlink solves this and will become the spine of the new financial system $Link #fintech", "replies_count": 1, "retweets_count": 6, "likes_count": 32, "Follower_count": 1367, "id_str": "1030096642429480960"}
