{"id": 1348993714711007232, "username": "xvix_finance", "created_at": "2021-01-12 19:32:19 IST", "tweet": "The XVIX project is proud to announce our integration of @chainlink price feed oracles into the X2 protocol   https://t.co/1c4wpYYJto", "replies_count": 12, "retweets_count": 155, "likes_count": 550, "Follower_count": 1994, "id_str": "1348993714711007232"}
{"id": 1348775450856878082, "username": "lilmoonlambo", "created_at": "2021-01-12 05:05:01 IST", "tweet": "Today will forever be known as the day $LINK started the legendary pump to $1000 and this was the final dip", "replies_count": 50, "retweets_count": 73, "likes_count": 919, "Follower_count": 107085, "id_str": "1348775450856878082"}
{"id": 1348756807494365184, "username": "koroushak", "created_at": "2021-01-12 03:50:56 IST", "tweet": "Yes I bought more $LINK.", "replies_count": 68, "retweets_count": 42, "likes_count": 1299, "Follower_count": 201218, "id_str": "1348756807494365184"}
{"id": 1348751525892546560, "username": "chainlink", "created_at": "2021-01-12 03:29:57 IST", "tweet": "Blockchain gaming dApps like @AxieInfinity, @EtherLegends, &amp; @DarwiniaNetwork\u2019s Evolution Land are integrating #Chainlink VRF to generate a secure source of randomness for in-game rewards, characters, &amp; more. Learn how to build with VRF in our docs below.  https://t.co/WqpcNhN1Ld", "replies_count": 12, "retweets_count": 111, "likes_count": 503, "Follower_count": 348204, "id_str": "1348751525892546560"}
{"id": 1348751556871663621, "username": "lilmoonlambo", "created_at": "2021-01-12 03:30:04 IST", "tweet": "broke: buying $LTC because it's the third biggest coin  woke: buying $LINK because it's actually the third biggest coin", "replies_count": 24, "retweets_count": 56, "likes_count": 607, "Follower_count": 107085, "id_str": "1348751556871663621"}
{"id": 1349040802169827331, "username": "messaricrypto", "created_at": "2021-01-12 22:39:25 IST", "tweet": "Of large cap tokens $LINK was the top performer of 2020, up 529% YoY  https://t.co/w2CRDrVvxA", "replies_count": 19, "retweets_count": 98, "likes_count": 355, "Follower_count": 121748, "id_str": "1349040802169827331"}
{"id": 1348926715184242688, "username": "santimentfeed", "created_at": "2021-01-12 15:06:05 IST", "tweet": "\ud83d\udc4b\ud83d\udd17\ud83d\udc5b As #altcoins have recovered to start the week, $LINK looks to be a standout in terms of its ratio of supply moving encouragingly away from exchanges. When this ratio moves more toward offline, it's an increasingly good sign of price upside.  https://t.co/NvgNlfSo61  https://t.co/NqIgrjHeI2", "replies_count": 13, "retweets_count": 78, "likes_count": 368, "Follower_count": 65755, "id_str": "1348926715184242688"}
{"id": 1348906822015483907, "username": "cointelegraph", "created_at": "2021-01-12 13:47:02 IST", "tweet": "Following massive growth, $XLM returns to the list of top-10 coins by market cap, beating $LINK and $BNB  https://t.co/JzUU6UriYS", "replies_count": 12, "retweets_count": 46, "likes_count": 280, "Follower_count": 983848, "id_str": "1348906822015483907"}
{"id": 1348759001572536323, "username": "pentosh1", "created_at": "2021-01-12 03:59:39 IST", "tweet": "I don't know how to tell you this.   I've been a filthy $Eth bull   But I also believe. $LINK and many #alts are about to wreck it for the next 6-8 weeks. This is bottom of several alt/eth pairs and alt $BTC pairs This is just one example. Sell your eth for alts. Then buy 2x eth  https://t.co/VMbl1RG9re", "replies_count": 31, "retweets_count": 43, "likes_count": 381, "Follower_count": 169133, "id_str": "1348759001572536323"}
{"id": 1348796211034206208, "username": "johncioffoletti", "created_at": "2021-01-12 06:27:30 IST", "tweet": "Always, always, always, buy the $LINK token dip. The amount is not as important as the practice. There is no other thought process to follow.", "replies_count": 20, "retweets_count": 39, "likes_count": 437, "Follower_count": 6996, "id_str": "1348796211034206208"}
{"id": 1348993882122559488, "username": "jwolpert", "created_at": "2021-01-12 19:32:59 IST", "tweet": "'2021 projects will start with\u00a0a focus of bringing together\u00a0internal\u00a0data\u2014but expanding\u00a0to\u00a0leverage external data by year close.'  Sounds like a job for @baselineproto and also #Chainlink  @SAP @AlessandroGasch  https://t.co/nrGWV9Hjsx", "replies_count": 8, "retweets_count": 62, "likes_count": 269, "Follower_count": 20072, "id_str": "1348993882122559488"}
{"id": 1348972736316657664, "username": "eliz883", "created_at": "2021-01-12 18:08:57 IST", "tweet": "I expect a big altcoin rocket very soon ... tic tok tic tok tic tok .... I have the cartridges ready $LINK $RSR $OCEAN \ud83d\udc40\ud83c\udfaf\u270d\ufe0f", "replies_count": 56, "retweets_count": 37, "likes_count": 378, "Follower_count": 51183, "id_str": "1348972736316657664"}
{"id": 1349032955872612352, "username": "chainlinkgod", "created_at": "2021-01-12 22:08:15 IST", "tweet": "Ground Floor Consensus podcast with @SergeyNazarov   One hour of based and $LINK-pilled content   https://t.co/fOCwAgqryg", "replies_count": 8, "retweets_count": 57, "likes_count": 256, "Follower_count": 86631, "id_str": "1349032955872612352"}
{"id": 1348700071848796161, "username": "defipuppet", "created_at": "2021-01-12 00:05:29 IST", "tweet": "You can't make this up. @CNBC is talking about @coinbase being down and how it affects futures markets because that is how they price their assets. They literally made an indirect endorsement of why we need @chainlink in this market! $LINK", "replies_count": 7, "retweets_count": 42, "likes_count": 381, "Follower_count": 724, "id_str": "1348700071848796161"}
{"id": 1348821935497621504, "username": "linknewsoracle", "created_at": "2021-01-12 08:09:43 IST", "tweet": "Ethereum gas prices spike to &gt;500 gwei.  #Chainlink data feeds did not miss a single update during this period.", "replies_count": 4, "retweets_count": 37, "likes_count": 368, "Follower_count": 53312, "id_str": "1348821935497621504"}
{"id": 1349044469534871552, "username": "cryptomichnl", "created_at": "2021-01-12 22:54:00 IST", "tweet": "#Chainlink also still consolidating nicely on the #Bitcoin pair as it's probably hit the support in that pair.  Copy/paste the momentum in March-May 2020 would be great.  If the $BTC pair reverses, I'd say a rally of 100% is likely.  https://t.co/KrhtQF4K3X", "replies_count": 5, "retweets_count": 37, "likes_count": 262, "Follower_count": 327924, "id_str": "1349044469534871552"}
{"id": 1348894984070598659, "username": "chainlinkgod", "created_at": "2021-01-12 13:00:00 IST", "tweet": "\"Higher throughput will enable us (@synthetix_io) in partnership with #Chainlink to reduce oracle latency, allowing for leverage via Synthetic Futures as well as a number of other protocol improvements\"  Layer 2 oracles coming soon my frens $SNX $LINK  https://t.co/LaNXALo99Q", "replies_count": 4, "retweets_count": 37, "likes_count": 257, "Follower_count": 86598, "id_str": "1348894984070598659"}
{"id": 1348797398315765760, "username": "crypto_bitc", "created_at": "2021-01-12 06:32:13 IST", "tweet": "$LINK is the way  Yes, I post a ton of charts \ud83d\udcc8  Helpful to see possible price action when trying to snipe solid entries  Time \u231b\ufe0f = Money \ud83d\udcb8  https://t.co/M1MFrGYCnq", "replies_count": 13, "retweets_count": 33, "likes_count": 261, "Follower_count": 15061, "id_str": "1348797398315765760"}
{"id": 1349050533282250764, "username": "profittmaker", "created_at": "2021-01-12 23:18:05 IST", "tweet": "$ETH is one cycle behind $BTC $LINK is one cycle behind $ETH $DIP is once cycle behind $LlNK", "replies_count": 15, "retweets_count": 32, "likes_count": 273, "Follower_count": 3133, "id_str": "1349050533282250764"}
{"id": 1349010341007663104, "username": "ayloalpha", "created_at": "2021-01-12 20:38:23 IST", "tweet": "ATH in number of daily transactions.   $50 $Link soon.  https://t.co/YfETk2FSRu", "replies_count": 9, "retweets_count": 30, "likes_count": 278, "Follower_count": 802, "id_str": "1349010341007663104"}
{"id": 1348965609372065794, "username": "lilmoonlambo", "created_at": "2021-01-12 17:40:38 IST", "tweet": "$LINK on the $BTC pair is finally starting to break out above a resistance that hasn't been tested since November, very bullish signs \ud83d\udc40  https://t.co/m3TLMwNIhe", "replies_count": 8, "retweets_count": 30, "likes_count": 189, "Follower_count": 107087, "id_str": "1348965609372065794"}
{"id": 1349032548257685508, "username": "thelinkmarine1", "created_at": "2021-01-12 22:06:37 IST", "tweet": "#Chainlink secures over $7B in value DeFi and is almost entirely the reason that #DeFi exists today.  Without secure reliable &amp; decentralized oracle networks like those offered by $LINK, DeFi smart contracts aren\u2019t really \u2018smart\u2019 or of much use at all.  #4IR #PoweredByChainlink", "replies_count": 1, "retweets_count": 35, "likes_count": 195, "Follower_count": 18907, "id_str": "1349032548257685508"}
{"id": 1348814585608822785, "username": "crypto___oracle", "created_at": "2021-01-12 07:40:31 IST", "tweet": "#Chainlink oracles should not be seen purely as entities that deliver data to smart contracts, but entities that perform a wide array of services for smart contracts that are not doable on the blockchain or not practical because of economic and/or performance limitations.", "replies_count": 8, "retweets_count": 28, "likes_count": 219, "Follower_count": 27360, "id_str": "1348814585608822785"}
{"id": 1348819468760264705, "username": "lilmoonlambo", "created_at": "2021-01-12 07:59:55 IST", "tweet": "Crypto Twitter IQ test:  When the demand of $LINK rises and the supply is decreasing from exchanges, what do you think happens?  https://t.co/Aahq3904Yc", "replies_count": 29, "retweets_count": 22, "likes_count": 200, "Follower_count": 107087, "id_str": "1348819468760264705"}
{"id": 1348747639316226053, "username": "lilmoonlambo", "created_at": "2021-01-12 03:14:30 IST", "tweet": "Imagine not buying $LINK here before we break through $20 and start going parabolic  https://t.co/bRzsTdFWEE", "replies_count": 8, "retweets_count": 17, "likes_count": 238, "Follower_count": 107085, "id_str": "1348747639316226053"}
{"id": 1348802089552646145, "username": "cryptokaleo", "created_at": "2021-01-12 06:50:52 IST", "tweet": "My friend who got me into crypto back in Jan 2017 just shilled me hard on the fundamentals of $AVAX. Charts look great.  This is the same friend who held the fat bag of $LINK from December of 2017 up until today. I didn't listen to him then. I'm not making the same mistake twice.  https://t.co/xvyaXzEZYy", "replies_count": 17, "retweets_count": 13, "likes_count": 155, "Follower_count": 316096, "id_str": "1348802089552646145"}
{"id": 1349046121566449666, "username": "cryptogodjohn", "created_at": "2021-01-12 23:00:34 IST", "tweet": "$OCEAN  Time is running out to accumulate big bags of OCEAN.  Data is the new oil, DATA will be a $30 trillion dollar industry by 2030. @oceanprotocol will be a leader in the data industry.  Strong fundamentals with this beast.  It will not surprised me when $OCEAN pulls a $LINK  https://t.co/V2RSEn4xiS", "replies_count": 7, "retweets_count": 27, "likes_count": 127, "Follower_count": 184154, "id_str": "1349046121566449666"}
{"id": 1349028861535805440, "username": "cryptogodjohn", "created_at": "2021-01-12 21:51:58 IST", "tweet": "Moon it all   $RSR $LINK $ETH \ud83d\ude80\ud83d\udd25", "replies_count": 7, "retweets_count": 14, "likes_count": 183, "Follower_count": 184154, "id_str": "1349028861535805440"}
{"id": 1349014953529925640, "username": "cryptogodjohn", "created_at": "2021-01-12 20:56:43 IST", "tweet": "Longed $ETH &amp; $LINK dip \ud83e\udd1d  Send it, please \ud83d\ude80", "replies_count": 9, "retweets_count": 13, "likes_count": 183, "Follower_count": 184154, "id_str": "1349014953529925640"}
{"id": 1349033336870756354, "username": "linkchainlink", "created_at": "2021-01-12 22:09:45 IST", "tweet": "$SNX is like the easy hot chick who you'd never date who loves to suck dick   $LINK is like the kindfaced soft precious woman who makes life worth living", "replies_count": 29, "retweets_count": 15, "likes_count": 272, "Follower_count": 11734, "id_str": "1349033336870756354"}
{"id": 1349045252347334656, "username": "cryptogodjohn", "created_at": "2021-01-12 22:57:06 IST", "tweet": "#Chainlink  If you do not think $LINK is going to absoutely fly in the coming weeks, you are WRONG.  Rumors of staking coming in early February.  Conservative target of $40 still stands  $LINK was the most bullish coin for 2 years, you think it won't run the hardest again? SHAME!  https://t.co/XPposq0E5i", "replies_count": 9, "retweets_count": 18, "likes_count": 129, "Follower_count": 184154, "id_str": "1349045252347334656"}
{"id": 1349036723364376578, "username": "quintenfrancois", "created_at": "2021-01-12 22:23:13 IST", "tweet": "Yes, and it's all #PoweredByChainlink. Why search for the next big project, while you can invest in a crucial piece of infrastructure necessary for the entire industry/niche?   $LINK", "replies_count": 9, "retweets_count": 19, "likes_count": 176, "Follower_count": 65110, "id_str": "1349036723364376578"}
{"id": 1348722050966450187, "username": "smart_contract", "created_at": "2021-01-12 01:32:49 IST", "tweet": "Join @HMsheikh4 and @Mettalex for a Q&amp;A tomorrow at 11 am ET live on the #Chainlink Youtube. Learn what makes Mettalex unique, their future roadmap, and Mettalex's use of @chainlink oracles.   RSVP here:  https://t.co/Jsj4equSvV", "replies_count": 3, "retweets_count": 33, "likes_count": 129, "Follower_count": 42112, "id_str": "1348722050966450187"}
{"id": 1348803101793386496, "username": "larrylogical", "created_at": "2021-01-12 06:54:53 IST", "tweet": "Question: Has anything \"fundamentally\" changed w/ $LINK?  Answer: No? Then it would behoove you to BUY THE DIP.  https://t.co/7f2Is95wkp", "replies_count": 11, "retweets_count": 23, "likes_count": 201, "Follower_count": 6604, "id_str": "1348803101793386496"}
{"id": 1348966130048786435, "username": "xvghulk", "created_at": "2021-01-12 17:42:42 IST", "tweet": "#chainlink $link #bitcoin #PoweredByChainlink  Yesterday:  Chainlink Holders: 333,019  Today:  Chainlink Holders: 334,761  \ud83d\udd39\ud83d\udd39\ud83d\udd39\ud83d\ude80 \ud83d\ude80 \ud83d\udd39\ud83d\udd39\ud83d\udd39", "replies_count": 3, "retweets_count": 26, "likes_count": 181, "Follower_count": 3508, "id_str": "1348966130048786435"}
{"id": 1348812497474695168, "username": "finrekt", "created_at": "2021-01-12 07:32:13 IST", "tweet": "Why is your token necessary?  #btc has the hodl meme   $eth is for gas  $link is for the retrieval and validation of objectively truthful data.   They still don\u2019t know about smart contracts. They still can\u2019t spell etherium.   You bought chainlink. Have faith anon.   God Christ!", "replies_count": 3, "retweets_count": 24, "likes_count": 176, "Follower_count": 12334, "id_str": "1348812497474695168"}
{"id": 1348784066657742856, "username": "lilmoonlambo", "created_at": "2021-01-12 05:39:15 IST", "tweet": "DeFi needs $LINK to succeed  What do you think happens to the price when institutions and retail find that out?  https://t.co/QjvK4yZz9u", "replies_count": 12, "retweets_count": 14, "likes_count": 153, "Follower_count": 107087, "id_str": "1348784066657742856"}
{"id": 1348844373967048705, "username": "cryptogodjohn", "created_at": "2021-01-12 09:38:53 IST", "tweet": "$LINK staking coming Q1  #Chainlink $40 incoming.", "replies_count": 4, "retweets_count": 14, "likes_count": 100, "Follower_count": 184153, "id_str": "1348844373967048705"}
{"id": 1349015069951221760, "username": "lilmoonlambo", "created_at": "2021-01-12 20:57:10 IST", "tweet": "DeFi is coming to the banking system.  DeFi needs $LINK.  Get ready \ud83d\ude80", "replies_count": 5, "retweets_count": 16, "likes_count": 123, "Follower_count": 107087, "id_str": "1349015069951221760"}
{"id": 1349039353205383168, "username": "crypto_bitc", "created_at": "2021-01-12 22:33:40 IST", "tweet": "How to turn 1 #Bitcoin into 3 w/ $LINK  https://t.co/mRRczgEb9B", "replies_count": 14, "retweets_count": 18, "likes_count": 184, "Follower_count": 15061, "id_str": "1349039353205383168"}
{"id": 1348995329736249345, "username": "don_chainlink", "created_at": "2021-01-12 19:38:44 IST", "tweet": "Chainlink @chainlink is on track towards breaking $100 within three years. Such a price movement would be an annual rate of return of 80%. $LINK supply is leaving exchanges and could be the first confirmation of short term bullishness.   $LINK   https://t.co/lbIIEof5Uy", "replies_count": 17, "retweets_count": 27, "likes_count": 140, "Follower_count": 10838, "id_str": "1348995329736249345"}
{"id": 1348779242960596993, "username": "macrocrg", "created_at": "2021-01-12 05:20:05 IST", "tweet": "Send it with haste &amp; growing confidence.   $LINK", "replies_count": 5, "retweets_count": 14, "likes_count": 157, "Follower_count": 58057, "id_str": "1348779242960596993"}
{"id": 1348735549931098113, "username": "crypto_bitc", "created_at": "2021-01-12 02:26:28 IST", "tweet": "$LINK compared to $ETH  Woah!  https://t.co/u4XqzWCedJ", "replies_count": 4, "retweets_count": 19, "likes_count": 165, "Follower_count": 15061, "id_str": "1348735549931098113"}
{"id": 1349051305793363974, "username": "don_chainlink", "created_at": "2021-01-12 23:21:10 IST", "tweet": "Chainlink @chainlink Community:   The best performing large cap of 2020 was $LINK (Also 2018 &amp; 2019) with the implementation of Threshold signatures, Off-Chain Computation, Mixicles, #DECO and Staking in 2021 expect much more of the same.   $LINK - You Just Win, OK;LG 2021.  https://t.co/UeS0DGc6I7", "replies_count": 3, "retweets_count": 27, "likes_count": 126, "Follower_count": 10838, "id_str": "1349051305793363974"}
{"id": 1349025504817524737, "username": "carpenoctom", "created_at": "2021-01-12 21:38:38 IST", "tweet": "my thoughts on $LINK here   https://t.co/sNwLJtIOBM  TLDR:  - team token selling continues - anything &lt;11 = buy  - anything &gt;60 = sell", "replies_count": 11, "retweets_count": 13, "likes_count": 75, "Follower_count": 136008, "id_str": "1349025504817524737"}
{"id": 1348795675719426048, "username": "lilmoonlambo", "created_at": "2021-01-12 06:25:23 IST", "tweet": "DeFi needs $LINK  https://t.co/f7Fwi04CtQ", "replies_count": 2, "retweets_count": 9, "likes_count": 117, "Follower_count": 107087, "id_str": "1348795675719426048"}
{"id": 1348733974898683906, "username": "finrekt", "created_at": "2021-01-12 02:20:12 IST", "tweet": "$LINK  https://t.co/jqAz8AaWhE", "replies_count": 8, "retweets_count": 14, "likes_count": 175, "Follower_count": 12334, "id_str": "1348733974898683906"}
{"id": 1348761271412383754, "username": "_chainlink_", "created_at": "2021-01-12 04:08:40 IST", "tweet": "Meanwhile in Chainlink Labs  $LINK  https://t.co/EW0dfT80cN", "replies_count": 3, "retweets_count": 22, "likes_count": 149, "Follower_count": 3262, "id_str": "1348761271412383754"}
{"id": 1348779891529945089, "username": "crypto_bitc", "created_at": "2021-01-12 05:22:39 IST", "tweet": "$LINK  Could it be?  What happens next?  https://t.co/kciuMnD5r8", "replies_count": 12, "retweets_count": 15, "likes_count": 147, "Follower_count": 15061, "id_str": "1348779891529945089"}
{"id": 1349030655422820354, "username": "thelinkmarine1", "created_at": "2021-01-12 21:59:06 IST", "tweet": "@USOCC @FinancialTimes @BrianBrooksOCC #Chainlink secures over $7B worth of smart contracts and is almost entirely the reason that #DeFi exists today.  Without secure reliable decentralized oracle networks like those provided by $LINK, DeFi smart contracts wouldn\u2019t very \u2018smart\u2019 or useful at all.  #PoweredByChainlink", "replies_count": 4, "retweets_count": 14, "likes_count": 147, "Follower_count": 18907, "id_str": "1349030655422820354"}
{"id": 1348941002183225344, "username": "link_hound", "created_at": "2021-01-12 16:02:51 IST", "tweet": "I laud any project that embraces the @chainlink proof of reserve function  I feel it's a nod towards transparency and truth  Congratulations Paxos Standard (PAX) @PaxosStandard   PAX / RESERVES is now live on #ETH mainnet  @PaxosStandard any comment for the #Chainlink community?  https://t.co/isK2pb2rze", "replies_count": 1, "retweets_count": 20, "likes_count": 136, "Follower_count": 7190, "id_str": "1348941002183225344"}
{"id": 1348870458398048256, "username": "fomo_the_fud", "created_at": "2021-01-12 11:22:32 IST", "tweet": "$LINK/BTC - 4hr  Possible bottom scenario?  Volume increase has me excite.  https://t.co/yPm1K4tyYl", "replies_count": 8, "retweets_count": 14, "likes_count": 172, "Follower_count": 4941, "id_str": "1348870458398048256"}
{"id": 1348786562012741640, "username": "linkchainlink", "created_at": "2021-01-12 05:49:10 IST", "tweet": "alot of $LINK leaving exchanges  https://t.co/tMu2nPaFpH", "replies_count": 11, "retweets_count": 11, "likes_count": 172, "Follower_count": 11734, "id_str": "1348786562012741640"}
{"id": 1349035076286345219, "username": "johncioffoletti", "created_at": "2021-01-12 22:16:40 IST", "tweet": "Exactly this \ud83d\udc47\ud83c\udffb\ud83d\udc47\ud83c\udffb\ud83d\udc47\ud83c\udffb  The Billions eventually become Trillions. $LINK #AllGreenLights", "replies_count": 1, "retweets_count": 15, "likes_count": 155, "Follower_count": 6996, "id_str": "1349035076286345219"}
{"id": 1349040921791385604, "username": "lilmoonlambo", "created_at": "2021-01-12 22:39:54 IST", "tweet": "@tyler @Filecoin DeFi needs $LINK", "replies_count": 4, "retweets_count": 0, "likes_count": 120, "Follower_count": 107087, "id_str": "1349040921791385604"}
{"id": 1348926499597012995, "username": "qquamfy", "created_at": "2021-01-12 15:05:14 IST", "tweet": "$QNT currently has 12k wallets.  At 50k wallets there's less than 300 Quant available for each.  Buy QNT while you can\ud83e\udd73  $BTC $XRP $ETH $LINK  https://t.co/Dtdb99hbBN", "replies_count": 13, "retweets_count": 26, "likes_count": 113, "Follower_count": 771, "id_str": "1348926499597012995"}
{"id": 1348844126368915458, "username": "lilmoonlambo", "created_at": "2021-01-12 09:37:54 IST", "tweet": "Now would be a good time to get back in $LINK @stoolpresidente", "replies_count": 3, "retweets_count": 6, "likes_count": 71, "Follower_count": 107087, "id_str": "1348844126368915458"}
{"id": 1348763853438341121, "username": "deepdishcrypto", "created_at": "2021-01-12 04:18:56 IST", "tweet": "The key to being #rich from #crypto is to find the coins like:  $XVG $LEND $AAVE $XRP $DOT $LINK $BTC $ETH $NEO $ADA $LTC   \u201cBEFORE\u201d they moon \ud83c\udf19 and #HODL on for dear life! $TEL is that next coin!  #remittance corridors opening end of  Jan! Partnerships! Regulatory Compliance!  https://t.co/BUFLytRrkJ", "replies_count": 6, "retweets_count": 28, "likes_count": 84, "Follower_count": 12036, "id_str": "1348763853438341121"}
{"id": 1348990095244853248, "username": "keeperofcoins", "created_at": "2021-01-12 19:17:56 IST", "tweet": "This guy gets it.  $LINK  https://t.co/a3knmBMTPb", "replies_count": 9, "retweets_count": 17, "likes_count": 142, "Follower_count": 1445, "id_str": "1348990095244853248"}
{"id": 1348776216103411714, "username": "adouble212", "created_at": "2021-01-12 05:08:03 IST", "tweet": "And if you think $1000 is crazy - understand that #DeFi doesn't take the next leap without $LINK", "replies_count": 5, "retweets_count": 4, "likes_count": 110, "Follower_count": 68372, "id_str": "1348776216103411714"}
{"id": 1348899389889257472, "username": "linkfinland", "created_at": "2021-01-12 13:17:30 IST", "tweet": "When 1,4 billion people have access to New Chinese Chainlink website and possibility to learn, it's huge $LINK #chainlink", "replies_count": 1, "retweets_count": 16, "likes_count": 127, "Follower_count": 6971, "id_str": "1348899389889257472"}
{"id": 1348739697800044555, "username": "linkchainlink", "created_at": "2021-01-12 02:42:56 IST", "tweet": "Sometimes you gotta DR;NS so you can OK;LG   $LINK", "replies_count": 2, "retweets_count": 10, "likes_count": 143, "Follower_count": 11734, "id_str": "1348739697800044555"}
{"id": 1348969244688588800, "username": "jjcycles", "created_at": "2021-01-12 17:55:05 IST", "tweet": "Meme inverse H&amp;S idea still alive.  $LINK / $BTC  https://t.co/lNvnRL1wTe", "replies_count": 4, "retweets_count": 5, "likes_count": 67, "Follower_count": 77849, "id_str": "1348969244688588800"}
{"id": 1348953665613271045, "username": "linkchainlink", "created_at": "2021-01-12 16:53:10 IST", "tweet": "$LINK should be valued at $10bn right now from proof of reserves alone  https://t.co/GyetVIAixX", "replies_count": 8, "retweets_count": 14, "likes_count": 111, "Follower_count": 11734, "id_str": "1348953665613271045"}
{"id": 1349041831443623938, "username": "linkchainlink", "created_at": "2021-01-12 22:43:31 IST", "tweet": "If $LINK users get big, they require more requests paid in $LINK which would drive up demand.   when $SNX + $AAVE grow $LINK will too  https://t.co/RzuI5s9BgJ", "replies_count": 6, "retweets_count": 9, "likes_count": 140, "Follower_count": 11734, "id_str": "1349041831443623938"}
{"id": 1349019950699212800, "username": "buttersdanklink", "created_at": "2021-01-12 21:16:34 IST", "tweet": "$LINK already is the standard. People just haven\u2019t realized it yet. \ud83d\udc8a\ud83e\udd86", "replies_count": 1, "retweets_count": 9, "likes_count": 168, "Follower_count": 3315, "id_str": "1349019950699212800"}
{"id": 1348704449129230344, "username": "thejonnyreid", "created_at": "2021-01-12 00:22:53 IST", "tweet": "BOOM - already 500m+ new native $kai staked on the @KardiaChain mainnet  Bare in mind - this is just the early stakers that entered the early swap.  Scary to see when the full swap happens!  Not going to be much supply left at all!   Incredible achievement   $OM $LINK $NEO $DOT  https://t.co/JbIyZ4GiP3", "replies_count": 9, "retweets_count": 17, "likes_count": 89, "Follower_count": 16204, "id_str": "1348704449129230344"}
{"id": 1348885835291103232, "username": "kaiynne", "created_at": "2021-01-12 12:23:38 IST", "tweet": "Asset expansion is critical to growing the network, this will likely include more crypto, commodities and FX but most importantly I expect the Spartan Council is likely to request Chainlink provide equities feeds as soon as they take control of the SIP process.", "replies_count": 3, "retweets_count": 7, "likes_count": 85, "Follower_count": 52192, "id_str": "1348885835291103232"}
{"id": 1349037498622648324, "username": "chainlinkgod", "created_at": "2021-01-12 22:26:18 IST", "tweet": "@nomos_paradox @TheLinkMarine1 @USOCC @FinancialTimes @BrianBrooksOCC Chainlink Price Feeds are the reason DeFi has grown at the pace it has, bootstrapped many applications", "replies_count": 2, "retweets_count": 2, "likes_count": 66, "Follower_count": 86598, "id_str": "1349037498622648324"}
{"id": 1348900336526884866, "username": "oli10k", "created_at": "2021-01-12 13:21:16 IST", "tweet": "Quant is changing the game \ud83d\udd25\ud83d\ude08 $QNT $BTC $ETH $LINK $XRP  https://t.co/yCtIbm79zc", "replies_count": 8, "retweets_count": 18, "likes_count": 111, "Follower_count": 3143, "id_str": "1348900336526884866"}
{"id": 1348767986463727620, "username": "scruffur", "created_at": "2021-01-12 04:35:21 IST", "tweet": "I\u2019m starting the transition from $ETH to ALTs   Just bought up that $RSR blood Bought more $ALBT $OCEAN $LINK $ORAI $BONDLY   Keeping a percentage spot $ETH to hedge.", "replies_count": 18, "retweets_count": 9, "likes_count": 93, "Follower_count": 27461, "id_str": "1348767986463727620"}
{"id": 1349002310786183168, "username": "don_chainlink", "created_at": "2021-01-12 20:06:28 IST", "tweet": "On-chain metrics for $LINK, Github dev activity, and Google Trends previously showed a strong or continuous uptick in activity in 2020. Over the past few weeks, all of these metrics have once again risen substantially.   @chainlink \u2935\ufe0f Technical Analysis.   https://t.co/v1XOxvRZyB", "replies_count": 2, "retweets_count": 15, "likes_count": 100, "Follower_count": 10838, "id_str": "1349002310786183168"}
{"id": 1348997551421349890, "username": "dec_future", "created_at": "2021-01-12 19:47:34 IST", "tweet": "Chainlink transactions today (12.1.2021): Ethereum mainnet: 125 057 tx Matic mainnet: 19 680 tx Binance mainnet: 14 990 tx Total: 159 727  Bitcoin daily transactions are today 331 000  #chainlink daily network transactions are ~0.5 x BTC - pretty bullish!   https://t.co/qvhr8wQQls", "replies_count": 3, "retweets_count": 18, "likes_count": 113, "Follower_count": 982, "id_str": "1348997551421349890"}
{"id": 1348940459360579585, "username": "linkchainlink", "created_at": "2021-01-12 16:00:42 IST", "tweet": "Most $LINK marines were down 5/6/7 figures on yesterday's move   All $LINK marines are still here.  https://t.co/ac6BSqheBf", "replies_count": 8, "retweets_count": 8, "likes_count": 128, "Follower_count": 11734, "id_str": "1348940459360579585"}
{"id": 1348916152345505800, "username": "santapacman", "created_at": "2021-01-12 14:24:07 IST", "tweet": "$QNT is Lead by the BEST Board across ALL #Crypto \ud83d\udc40\ud83d\udd25  \u2705 Guy Dietrich, Manager #RockefellerCapital \u2705 Paolo Tasca, Co-founder &amp; Director #UCLcbt  \u2705 Neil Smit, CEO #Comcast   $BTC $ETH $BNB $XEM $LTC $BCH $ZIL $XRP $LINK $BNB $DOT $YFI $VET $ADA $UNI #XRPCommunity #altseason  https://t.co/gFwb5d7dtC", "replies_count": 2, "retweets_count": 28, "likes_count": 82, "Follower_count": 531, "id_str": "1348916152345505800"}
{"id": 1348749987748970496, "username": "silverbulletbtc", "created_at": "2021-01-12 03:23:50 IST", "tweet": "@LilMoonLambo Soon price discovery $LINK will run hard once the fomo kicks in", "replies_count": 3, "retweets_count": 3, "likes_count": 74, "Follower_count": 55592, "id_str": "1348749987748970496"}
{"id": 1348983073602498560, "username": "utoday_en", "created_at": "2021-01-12 18:50:02 IST", "tweet": "\ud83d\udd25 More and more @chainlink $LINK tokens are moved from exchanges, analysts @santimentfeed say w/ @CryptoDavid_ @chainlinkgod @linkfinland #Chainlink #LINK  https://t.co/4iSKkwgpRq", "replies_count": 0, "retweets_count": 11, "likes_count": 69, "Follower_count": 34407, "id_str": "1348983073602498560"}
{"id": 1348798955400929280, "username": "linkchainlink", "created_at": "2021-01-12 06:38:25 IST", "tweet": "We are going to witness one of the strongest bounces known to man.  $LINK $BTC $ETH $LINK  https://t.co/Jmx1WRdLpG", "replies_count": 11, "retweets_count": 5, "likes_count": 138, "Follower_count": 11734, "id_str": "1348798955400929280"}
{"id": 1348705973721059328, "username": "linkchainlink", "created_at": "2021-01-12 00:28:56 IST", "tweet": "If you're not buying $LINK here, you're indirectly buying poor  https://t.co/2L2O5Xgn3Q", "replies_count": 6, "retweets_count": 11, "likes_count": 100, "Follower_count": 11734, "id_str": "1348705973721059328"}
{"id": 1348976882633461760, "username": "odailychina", "created_at": "2021-01-12 18:25:26 IST", "tweet": "Recording link of the online panel\u201c Future of #DeFi\u201d:   https://t.co/5y9z95c4QT Thanks for attending @SergeyNazarov @deacix @StaniKulechov @Diane_0320 @daniel_loopring, happy to hear the leading edge of thoughts from @chainlink @1inchExchange @AaveAave @BreederDodo @loopringorg  https://t.co/bIEamUUfpG", "replies_count": 9, "retweets_count": 23, "likes_count": 84, "Follower_count": 1206, "id_str": "1348976882633461760"}
{"id": 1348875349321342976, "username": "crypto_bitc", "created_at": "2021-01-12 11:41:58 IST", "tweet": "That was the $LINK dip   How did you do?  We\u2019re you able to remember how bullish it was even through the dip?", "replies_count": 7, "retweets_count": 8, "likes_count": 100, "Follower_count": 15061, "id_str": "1348875349321342976"}
{"id": 1348741539694931968, "username": "crypto_bitc", "created_at": "2021-01-12 02:50:16 IST", "tweet": "After this point in time $ETH then went an additional 1500% or 15x \ud83d\ude80  This would put $LINK at around $250 by years end \ud83d\udcb8  https://t.co/ynU2fx54jB", "replies_count": 7, "retweets_count": 10, "likes_count": 89, "Follower_count": 15061, "id_str": "1348741539694931968"}
{"id": 1348764690214739969, "username": "chainlinkoracie", "created_at": "2021-01-12 04:22:15 IST", "tweet": "$LINK to top3 EOY   Easily. I mean look at that.  https://t.co/kVwOMStnce", "replies_count": 9, "retweets_count": 5, "likes_count": 144, "Follower_count": 6600, "id_str": "1348764690214739969"}
{"id": 1349008869079588868, "username": "chartslink", "created_at": "2021-01-12 20:32:32 IST", "tweet": "#Chainlink regenerating \ud83c\udf31  Reasons to continue to grow \ud83c\udf3c - Price above Kijun and cloud \ud83e\uddd9\u200d\u2642\ufe0f - Chikou in blue sky \ud83e\udd16 - $LINK above 100/200 Day \ud83e\udd18 - 100/200 Day angling \u2b06\ufe0f - Green cloud fattening \ud83c\udf85 - Macro bull market \ud83d\udcc8 - Kijun offering support \ud83d\udcaa - It's still under $50 \ud83d\udcb0  https://t.co/spFctGvfoE", "replies_count": 0, "retweets_count": 13, "likes_count": 97, "Follower_count": 5116, "id_str": "1349008869079588868"}
{"id": 1348785621419122689, "username": "amjed_ababseh", "created_at": "2021-01-12 05:45:26 IST", "tweet": "#Telcoin roadmap is jam packed for Q1 and Q2 don\u2019t get left behind boys and girls!!!  $Tel $Vidt #Btc #Eth $Xrp $Link $Dot $Zil $Ada $Ltc  https://t.co/55hMskmKQ6", "replies_count": 5, "retweets_count": 27, "likes_count": 72, "Follower_count": 477, "id_str": "1348785621419122689"}
{"id": 1348999029519167490, "username": "jwolpert", "created_at": "2021-01-12 19:53:26 IST", "tweet": "@LinkiesLeaks @baselineproto @SAP @AlessandroGasch @BandProtocol @API3DAO I haven't heard of those. Just need good marketplace of consistent data sources to use in function parameters. Chainlink seems on track to be the largest source with best brand. Their game to lose. Baseliners are just consumers of the capability.", "replies_count": 5, "retweets_count": 6, "likes_count": 78, "Follower_count": 20072, "id_str": "1348999029519167490"}
{"id": 1348965847944097792, "username": "linkchainlink", "created_at": "2021-01-12 17:41:35 IST", "tweet": "$LINK could be at $10 and we'd all still be rich as fuck  Add another zero new ATH this month  https://t.co/qDEQHdh3IN", "replies_count": 2, "retweets_count": 5, "likes_count": 106, "Follower_count": 11734, "id_str": "1348965847944097792"}
{"id": 1348737417021444097, "username": "rbryer23", "created_at": "2021-01-12 02:33:53 IST", "tweet": "All of these entities relying on a single #CoinBase price feed when we have $LINK to decentralize and ensure reliable data in 2021 ...  #Bitcoin boomers aren't ready for #ChainLink but their kids are going to love it. \ud83d\udda4", "replies_count": 5, "retweets_count": 7, "likes_count": 87, "Follower_count": 13017, "id_str": "1348737417021444097"}
{"id": 1348751507127115776, "username": "crypto_bitc", "created_at": "2021-01-12 03:29:52 IST", "tweet": "I want nothing more than for everyone to become financially stable and comfy because of $LINK  Short Term | Large % gains   Long Term | Passive income from large #Chainlink holdings  $LINK \u2018s utility is a MUST if crypto is going to do what we think it can  #NeverSelling", "replies_count": 3, "retweets_count": 4, "likes_count": 100, "Follower_count": 15061, "id_str": "1348751507127115776"}
{"id": 1348950623543242752, "username": "loverplaid", "created_at": "2021-01-12 16:41:05 IST", "tweet": "If @Tether_to used @Chainlink's Proof of Reserves, there would be no #Tether FUD $USDT", "replies_count": 7, "retweets_count": 7, "likes_count": 118, "Follower_count": 2801, "id_str": "1348950623543242752"}
{"id": 1348955562810220545, "username": "jos_crypto", "created_at": "2021-01-12 17:00:43 IST", "tweet": "Buy $LINK  Its going to $18 very soon", "replies_count": 10, "retweets_count": 4, "likes_count": 125, "Follower_count": 5486, "id_str": "1348955562810220545"}
{"id": 1348744477477724160, "username": "crypto_bitc", "created_at": "2021-01-12 03:01:56 IST", "tweet": "The moment someone asks me what $LINK is I immediately take a huge breathe and at a loss for words  Depends on how knowledgeable they are about crypto in general, but it always ends with them saying the same thing...  \"Woah..it applies to everything? it has no competition?\"", "replies_count": 3, "retweets_count": 7, "likes_count": 75, "Follower_count": 15061, "id_str": "1348744477477724160"}
{"id": 1349054184960757762, "username": "littlelinkgath1", "created_at": "2021-01-12 23:32:36 IST", "tweet": "All this talk about DeFi exploding and the future of finance etc.  You realize DeFi literally can\u2019t work and won\u2019t exist safely without $LINK?", "replies_count": 6, "retweets_count": 11, "likes_count": 92, "Follower_count": 2078, "id_str": "1349054184960757762"}
{"id": 1349051187442683905, "username": "finrekt", "created_at": "2021-01-12 23:20:41 IST", "tweet": "Layer 2 solutions on ethereum will drastically reduce gas costs thereby reducing demand for $eth  There are no layer 2 solutions for secure and reliable oracles  1 $link &gt; 1 $eth   soon  few", "replies_count": 4, "retweets_count": 5, "likes_count": 83, "Follower_count": 12334, "id_str": "1349051187442683905"}
{"id": 1348843060101308418, "username": "don_chainlink", "created_at": "2021-01-12 09:33:40 IST", "tweet": "@chainlink This is excellent news, the largest population on earth now has access to Chainlink in their native language.   $LINK - China has just been LINKPilled. OK;LG 2021.  https://t.co/y5gJIvmMgn", "replies_count": 0, "retweets_count": 7, "likes_count": 78, "Follower_count": 10838, "id_str": "1348843060101308418"}
{"id": 1349006487927070720, "username": "drewbarnes85", "created_at": "2021-01-12 20:23:04 IST", "tweet": "Chainlink | GTA5 | PS4  https://t.co/0SxSRSLi6V", "replies_count": 3, "retweets_count": 23, "likes_count": 56, "Follower_count": 2391, "id_str": "1349006487927070720"}
{"id": 1348703025951510528, "username": "crypto_bitc", "created_at": "2021-01-12 00:17:13 IST", "tweet": "Gotta love $LINK trend lines  https://t.co/n5PIR7T8qG", "replies_count": 1, "retweets_count": 4, "likes_count": 80, "Follower_count": 15061, "id_str": "1348703025951510528"}
{"id": 1348752211048878082, "username": "linkmarine2000", "created_at": "2021-01-12 03:32:40 IST", "tweet": "Been here from $2.66-$1.50, $4.70-1.80, and $20-$7.50 and never once have I thought about selling a single $LINK.", "replies_count": 5, "retweets_count": 4, "likes_count": 109, "Follower_count": 5082, "id_str": "1348752211048878082"}
{"id": 1348982374248443909, "username": "matsjulner", "created_at": "2021-01-12 18:47:15 IST", "tweet": "$albt $ocean $link $qnt $ramp \ud83e\udd14  https://t.co/cOlsmLxhVG", "replies_count": 7, "retweets_count": 15, "likes_count": 85, "Follower_count": -1, "id_str": "1348982374248443909"}
{"id": 1349003525674717184, "username": "____vinci", "created_at": "2021-01-12 20:11:18 IST", "tweet": "Everytime we get an integration on $LINK it reminds me that we\u2019re only waiting on reality to catch up in terms of token price. Literally hundreds of teams, and CL team making new connections with new projects all the time all over the world.  Undervalued, but comfy AF!", "replies_count": 4, "retweets_count": 7, "likes_count": 99, "Follower_count": 2521, "id_str": "1349003525674717184"}
{"id": 1348712962031120384, "username": "crypto_bitc", "created_at": "2021-01-12 00:56:42 IST", "tweet": "$LINK always lines up \ud83d\udcc8  Place your bets \ud83c\udf40\ud83d\udcb8  https://t.co/lEwJuih1fW", "replies_count": 4, "retweets_count": 4, "likes_count": 65, "Follower_count": 15061, "id_str": "1348712962031120384"}
{"id": 1348756367776034816, "username": "chainlinkoracie", "created_at": "2021-01-12 03:49:11 IST", "tweet": "Reminder:  $Link will hit $100 by summer.   Yes.  How do I know that?  IYKYK  few  https://t.co/iUNf2Tq90e", "replies_count": 9, "retweets_count": 3, "likes_count": 97, "Follower_count": 6600, "id_str": "1348756367776034816"}
{"id": 1349028868368302080, "username": "linkchainlink", "created_at": "2021-01-12 21:52:00 IST", "tweet": "$AAVE and $SNX are the poster boys of integrating $LINK   Symbiotic winning. More to come  https://t.co/CZMbAtFtUX", "replies_count": 3, "retweets_count": 4, "likes_count": 75, "Follower_count": 11734, "id_str": "1349028868368302080"}
{"id": 1348996840738484228, "username": "jwolpert", "created_at": "2021-01-12 19:44:44 IST", "tweet": "@LinkiesLeaks @baselineproto @SAP @AlessandroGasch Sure..the case described in the article clearly calls for oracles. Last I checked, Chainlink is a leading provider of that, no?", "replies_count": 1, "retweets_count": 3, "likes_count": 54, "Follower_count": 20072, "id_str": "1348996840738484228"}
{"id": 1349029583593607169, "username": "oraclehershiser", "created_at": "2021-01-12 21:54:51 IST", "tweet": "$LINK/BTC coiling up... FFS SEND  https://t.co/h03waaNotf", "replies_count": 1, "retweets_count": 8, "likes_count": 90, "Follower_count": 2298, "id_str": "1349029583593607169"}
{"id": 1348780509615300616, "username": "linkchainlink", "created_at": "2021-01-12 05:25:07 IST", "tweet": "$LINK TOP IN", "replies_count": 10, "retweets_count": 0, "likes_count": 92, "Follower_count": 11734, "id_str": "1348780509615300616"}
{"id": 1348870632239370247, "username": "sterlingdefis", "created_at": "2021-01-12 11:23:14 IST", "tweet": "I\u2019ve said it before and I\u2019ll say it again, Spartan Marines are going to dominate 2021. $Link $Snx  https://t.co/jPhQLxZEFt", "replies_count": 1, "retweets_count": 4, "likes_count": 105, "Follower_count": 2892, "id_str": "1348870632239370247"}
{"id": 1349031928578469893, "username": "chainlinkp", "created_at": "2021-01-12 22:04:10 IST", "tweet": "Interesting read. The writing is on the wall. They know what's coming.  There's no way regulation doesn't find it's way towards understanding the virtues of decentralized oracles in \"self-driving banks\".  This will play it's way into exactly what #Chainlink does.  https://t.co/V7WN7snvkc", "replies_count": 1, "retweets_count": 7, "likes_count": 56, "Follower_count": 11078, "id_str": "1349031928578469893"}
{"id": 1348704458566340608, "username": "linkorbust", "created_at": "2021-01-12 00:22:55 IST", "tweet": "Breaking News: If you panic sold your $LINK, Stay Poor.  Strong hands make it out of bull markets alive  https://t.co/XEfEkFHbBu", "replies_count": 2, "retweets_count": 4, "likes_count": 69, "Follower_count": 8788, "id_str": "1348704458566340608"}
{"id": 1348763756914946049, "username": "sirlinkiest", "created_at": "2021-01-12 04:18:33 IST", "tweet": "opening the calculator app and multiplying future $link price against my stack  https://t.co/GERAav6oss", "replies_count": 6, "retweets_count": 8, "likes_count": 74, "Follower_count": 2276, "id_str": "1348763756914946049"}
{"id": 1348893912522436609, "username": "cryptodavid_", "created_at": "2021-01-12 12:55:44 IST", "tweet": "Oh wow, technical pace is brutal but also communication efforts are being doubled down too.   $LINK #Chainlink", "replies_count": 1, "retweets_count": 4, "likes_count": 65, "Follower_count": 8582, "id_str": "1348893912522436609"}
{"id": 1348735519853850626, "username": "____vinci", "created_at": "2021-01-12 02:26:20 IST", "tweet": "$LINK \u00a31000 EOY  Bongs unite", "replies_count": 5, "retweets_count": 4, "likes_count": 89, "Follower_count": 2521, "id_str": "1348735519853850626"}
{"id": 1349030171685363714, "username": "linkmarine2000", "created_at": "2021-01-12 21:57:11 IST", "tweet": "if $LINK staking rewards are &gt;7.77% I\u2019m telling my future boss to go fuck themselves.", "replies_count": 3, "retweets_count": 3, "likes_count": 79, "Follower_count": 5082, "id_str": "1349030171685363714"}
{"id": 1348842351511416834, "username": "finrekt", "created_at": "2021-01-12 09:30:51 IST", "tweet": "@chainlink Chinesepilled  https://t.co/y9vaB794rd", "replies_count": 1, "retweets_count": 0, "likes_count": 64, "Follower_count": 12334, "id_str": "1348842351511416834"}
{"id": 1348701836707041281, "username": "miss_aneleee", "created_at": "2021-01-12 00:12:30 IST", "tweet": "One day! $link  https://t.co/TMJeqQbZGF", "replies_count": 8, "retweets_count": 4, "likes_count": 86, "Follower_count": 2140, "id_str": "1348701836707041281"}
{"id": 1348721955898183680, "username": "chainlinkbull", "created_at": "2021-01-12 01:32:26 IST", "tweet": "$albt is the real $link according to gambling wizard", "replies_count": 17, "retweets_count": 0, "likes_count": 49, "Follower_count": 11783, "id_str": "1348721955898183680"}
{"id": 1348975127984300033, "username": "geminhighc", "created_at": "2021-01-12 18:18:27 IST", "tweet": "Keep hearing about $QNT.  I have $LINK, $ALBT &amp; $DIP  Is $QNT the missing link?", "replies_count": 21, "retweets_count": 1, "likes_count": 93, "Follower_count": 2500, "id_str": "1348975127984300033"}
{"id": 1349050107229052932, "username": "chainlinkoracie", "created_at": "2021-01-12 23:16:24 IST", "tweet": "&gt;After staring LINK/USD 1 second candles for 3 years  $link  https://t.co/b6gLj7VLor", "replies_count": 7, "retweets_count": 2, "likes_count": 70, "Follower_count": 6600, "id_str": "1349050107229052932"}
{"id": 1348784867081932801, "username": "linkchainlink", "created_at": "2021-01-12 05:42:26 IST", "tweet": "Long live the $LINK marines  https://t.co/1Xo7oEWVaA", "replies_count": 3, "retweets_count": 0, "likes_count": 59, "Follower_count": 11734, "id_str": "1348784867081932801"}
{"id": 1348870349677584384, "username": "rbryer23", "created_at": "2021-01-12 11:22:06 IST", "tweet": "Carry on $LINK \ud83d\udfe9", "replies_count": 1, "retweets_count": 2, "likes_count": 46, "Follower_count": 13017, "id_str": "1348870349677584384"}
{"id": 1349013435296718848, "username": "linkorbust", "created_at": "2021-01-12 20:50:41 IST", "tweet": "Yeah I hold $LINK how\u2019d you know?  https://t.co/zP1PwNWtS2", "replies_count": 2, "retweets_count": 3, "likes_count": 54, "Follower_count": 8788, "id_str": "1349013435296718848"}
{"id": 1348977975803445248, "username": "larrylogical", "created_at": "2021-01-12 18:29:46 IST", "tweet": "TL;DR we're early and they aren't slowing down.  $LINK  https://t.co/Zr2eV2pkpR", "replies_count": 5, "retweets_count": 5, "likes_count": 51, "Follower_count": 6604, "id_str": "1348977975803445248"}
{"id": 1349038701033218051, "username": "loverplaid", "created_at": "2021-01-12 22:31:04 IST", "tweet": "Tweeting at @elonmusk about @chainlink until he responds to @Hushhhbruh day 4 $LINK   https://t.co/wBb0rBnxD3", "replies_count": 0, "retweets_count": 6, "likes_count": 68, "Follower_count": 2801, "id_str": "1349038701033218051"}
{"id": 1348750489895243778, "username": "potheadphrog777", "created_at": "2021-01-12 03:25:50 IST", "tweet": "Wifey found the Chainlink Cult group chat \ud83d\ude30\ud83d\ude25 wish me luck Frens", "replies_count": 10, "retweets_count": 0, "likes_count": 95, "Follower_count": 3193, "id_str": "1348750489895243778"}
{"id": 1348992459561447425, "username": "chainlinkoracie", "created_at": "2021-01-12 19:27:20 IST", "tweet": "&gt;he thought this is the end of the multi-year bullrun which started in july 2018 with bi-weekly integrations, continued with Town Crier aqcuisition, succesfull mainnet launch, Google Cloud integration, mixicles, DECO acquisiton, @WEF whitepaper, Chainlink labs..  Anon, I..  $link  https://t.co/0aYkZHypwD", "replies_count": 2, "retweets_count": 3, "likes_count": 55, "Follower_count": 6600, "id_str": "1348992459561447425"}
{"id": 1348797449712766977, "username": "colorado_crypto", "created_at": "2021-01-12 06:32:26 IST", "tweet": "You guys and gals really are some of my best frens! Most don\u2019t understand. \ud83d\udc9a\ud83d\udc9a\ud83d\udc9a $Link", "replies_count": 7, "retweets_count": 1, "likes_count": 93, "Follower_count": 1715, "id_str": "1348797449712766977"}
{"id": 1348722976229896193, "username": "hushhhbruh", "created_at": "2021-01-12 01:36:30 IST", "tweet": "tweeting about $link at @elonmusk until he replies. day 107", "replies_count": 3, "retweets_count": 1, "likes_count": 82, "Follower_count": 3296, "id_str": "1348722976229896193"}
{"id": 1348933325843554305, "username": "chainlinkoracie", "created_at": "2021-01-12 15:32:21 IST", "tweet": "Be careful $link'ies  This offensive buzz phrase will get you banned from social media in 2022:  https://t.co/sPpZuZSzyQ", "replies_count": 2, "retweets_count": 2, "likes_count": 51, "Follower_count": 6600, "id_str": "1348933325843554305"}
{"id": 1348727382807511040, "username": "permabulltard", "created_at": "2021-01-12 01:54:00 IST", "tweet": "When someone told you coin A is bigger than $LINK. He doesn\u2019t know what he\u2019s talking about.", "replies_count": 3, "retweets_count": 2, "likes_count": 75, "Follower_count": 2515, "id_str": "1348727382807511040"}
{"id": 1348837587394375682, "username": "tylercolvard", "created_at": "2021-01-12 09:11:55 IST", "tweet": "Serious question: will there be yachts on the moon? $link $rsr", "replies_count": 6, "retweets_count": 3, "likes_count": 55, "Follower_count": 3783, "id_str": "1348837587394375682"}
{"id": 1348699539172163584, "username": "pickle_crypto", "created_at": "2021-01-12 00:03:22 IST", "tweet": "Shoutout to the man with the $LINK hopium at all times", "replies_count": 3, "retweets_count": 2, "likes_count": 69, "Follower_count": 2533, "id_str": "1348699539172163584"}
{"id": 1348771527337119762, "username": "linkmarine2000", "created_at": "2021-01-12 04:49:25 IST", "tweet": "Who wanna buy $LINK w me rn?", "replies_count": 4, "retweets_count": 1, "likes_count": 54, "Follower_count": 5082, "id_str": "1348771527337119762"}
{"id": 1348949239536242688, "username": "tylercolvard", "created_at": "2021-01-12 16:35:35 IST", "tweet": "Am I way overexposed? Yes. Do I feel drastically underexposed and end up buying more? Yes. My right-now self is crazy, but my future self is a genius $btc $eth $link $vet $rsr $ubt", "replies_count": 2, "retweets_count": 3, "likes_count": 48, "Follower_count": 3783, "id_str": "1348949239536242688"}
{"id": 1348820181859131396, "username": "colorado_crypto", "created_at": "2021-01-12 08:02:45 IST", "tweet": "Inverse head and shoulders knees and toes. 1h. $Link \ud83d\ude80", "replies_count": 1, "retweets_count": 1, "likes_count": 69, "Follower_count": 1715, "id_str": "1348820181859131396"}
{"id": 1348795066555330560, "username": "papaya_link", "created_at": "2021-01-12 06:22:57 IST", "tweet": "ACCUMULATION CYLINDER.  If you know , you know. :)  $LINK #CHAINLINK", "replies_count": 4, "retweets_count": 1, "likes_count": 60, "Follower_count": 1752, "id_str": "1348795066555330560"}
{"id": 1348986371583733762, "username": "l1nk68", "created_at": "2021-01-12 19:03:08 IST", "tweet": "Suicide stack 10,000 $LINK 10,000 $ETH 10,000 $BTC 10,000 $ALBT  It\u2019s that easy", "replies_count": 10, "retweets_count": 2, "likes_count": 59, "Follower_count": 773, "id_str": "1348986371583733762"}
{"id": 1348841490643120129, "username": "ahmedfalafal", "created_at": "2021-01-12 09:27:26 IST", "tweet": "ChainLink is bigger than Sergey. $LINK", "replies_count": 4, "retweets_count": 0, "likes_count": 65, "Follower_count": 1164, "id_str": "1348841490643120129"}
{"id": 1348704571133026305, "username": "coinwise_qvq", "created_at": "2021-01-12 00:23:22 IST", "tweet": "@woonomic @Chainlink helps here. Coinbase has other issues too but getting your price oracle solved is table stakes.", "replies_count": 1, "retweets_count": 0, "likes_count": 66, "Follower_count": 1245, "id_str": "1348704571133026305"}
{"id": 1349034716364759041, "username": "permabulltard", "created_at": "2021-01-12 22:15:14 IST", "tweet": "I sold $SNX at $0.50. I thought it didn\u2019t go anywhere and no way a retard will make it by clicking a button every week.   $BTC $ETH $LINK", "replies_count": 8, "retweets_count": 0, "likes_count": 42, "Follower_count": 2515, "id_str": "1349034716364759041"}
{"id": 1349023579489378311, "username": "piepmannscher", "created_at": "2021-01-12 21:30:59 IST", "tweet": "Last night i had the strangest dream $LINK  https://t.co/pd8ZecVx4e", "replies_count": 7, "retweets_count": 3, "likes_count": 53, "Follower_count": 444, "id_str": "1349023579489378311"}
